toxichempy/__init__.py
toxichempy/_env_check.py
toxichempy/chemoinformatics/__init__.py
toxichempy/chemoinformatics/molecular_descriptors.py
toxichempy/cli.py
toxichempy/computational_toxicology/__init__.py
toxichempy/data/iris.csv
toxichempy/data_collection/__init__.py
toxichempy/data_loader.py
toxichempy/experimental_toxicology/__init__.py
toxichempy/machine_learning/__init__.py
toxichempy/pipeline_framework/__init__.py
toxichempy/pipeline_framework/aop_data copy.py
toxichempy/pipeline_framework/aop_data.py
toxichempy/pipeline_framework/bioassay_data_for_ml.py
toxichempy/pipeline_framework/bioassy_data_for_ml copy.py
toxichempy/risk_assessment/__init__.py
toxichempy/statistical_analysis/__init__.py
toxichempy/utils/__init__.py
toxichempy/utils/data_io_utils.py
toxichempy/visualization/__init__.py
toxichempy-0.1.3.dist-info/entry_points.txt
toxichempy-0.1.3.dist-info/LICENSE
toxichempy-0.1.3.dist-info/METADATA
toxichempy-0.1.3.dist-info/WHEEL
toxichempy-0.1.3.dist-info/RECORD
